pyansi3/__init__.py
pyansi3/pyansi3.py
py_ansi3-1.2.1.dist-info/LICENSE
py_ansi3-1.2.1.dist-info/METADATA
py_ansi3-1.2.1.dist-info/WHEEL
py_ansi3-1.2.1.dist-info/top_level.txt
py_ansi3-1.2.1.dist-info/RECORD
