Metadata-Version: 2.1
Name: py-ansi3
Version: 1.2.1
Summary: 🔗 Package Guide On https://github.com/mohamedlunar/PyANSI3
Home-page: https://github.com/mohamedlunar/PyANSI3
Author: MohamedLunar
Author-email: contact.mohamedlunardev@gmail.com
Classifier: Programming Language :: Python :: 3
Classifier: License :: OSI Approved :: MIT License
Classifier: Operating System :: OS Independent
License-File: LICENSE
